django_roadtrip/__init__.py
django_roadtrip/admin.py
django_roadtrip/apps.py
django_roadtrip/migrations/0001_initial.py
django_roadtrip/migrations/0002_auto_20190619_0937.py
django_roadtrip/migrations/0003_auto_20190619_0947.py
django_roadtrip/migrations/__init__.py
django_roadtrip/models.py
django_roadtrip/templates/roadtrip/base.html
django_roadtrip/templates/roadtrip/error.html
django_roadtrip/templates/roadtrip/index.html
django_roadtrip/templates/roadtrip/partials/card-fuel.html
django_roadtrip/templates/roadtrip/profile.html
django_roadtrip/templates/roadtrip/roadtrip.html
django_roadtrip/tests.py
django_roadtrip/urls.py
django_roadtrip/views.py
django_roadtrip-0.1.0.dist-info/LICENSE
django_roadtrip-0.1.0.dist-info/WHEEL
django_roadtrip-0.1.0.dist-info/METADATA
django_roadtrip-0.1.0.dist-info/RECORD
